alsa_ctl/__init__.py
alsa_ctl/_version.py
alsa_ctl/cli.py
alsa_ctl/lib.py
alsa_ctl/completion/_alsa-ctl
alsa_ctl-0.1.3.data/scripts/alsa-ctl
alsa_ctl-0.1.3.dist-info/LICENSE
alsa_ctl-0.1.3.dist-info/METADATA
alsa_ctl-0.1.3.dist-info/WHEEL
alsa_ctl-0.1.3.dist-info/top_level.txt
alsa_ctl-0.1.3.dist-info/RECORD
